font_source_sans_pro/__init__.py
font_source_sans_pro/files/LICENSE.txt
font_source_sans_pro/files/SourceSansPro-Black.otf
font_source_sans_pro/files/SourceSansPro-Black.ttf
font_source_sans_pro/files/SourceSansPro-BlackIt.otf
font_source_sans_pro/files/SourceSansPro-BlackIt.ttf
font_source_sans_pro/files/SourceSansPro-Bold.otf
font_source_sans_pro/files/SourceSansPro-Bold.ttf
font_source_sans_pro/files/SourceSansPro-BoldIt.otf
font_source_sans_pro/files/SourceSansPro-BoldIt.ttf
font_source_sans_pro/files/SourceSansPro-ExtraLight.otf
font_source_sans_pro/files/SourceSansPro-ExtraLight.ttf
font_source_sans_pro/files/SourceSansPro-ExtraLightIt.otf
font_source_sans_pro/files/SourceSansPro-ExtraLightIt.ttf
font_source_sans_pro/files/SourceSansPro-It.otf
font_source_sans_pro/files/SourceSansPro-It.ttf
font_source_sans_pro/files/SourceSansPro-Light.otf
font_source_sans_pro/files/SourceSansPro-Light.ttf
font_source_sans_pro/files/SourceSansPro-LightIt.otf
font_source_sans_pro/files/SourceSansPro-LightIt.ttf
font_source_sans_pro/files/SourceSansPro-Regular.otf
font_source_sans_pro/files/SourceSansPro-Regular.ttf
font_source_sans_pro/files/SourceSansPro-Semibold.otf
font_source_sans_pro/files/SourceSansPro-Semibold.ttf
font_source_sans_pro/files/SourceSansPro-SemiboldIt.otf
font_source_sans_pro/files/SourceSansPro-SemiboldIt.ttf
font_source_sans_pro-0.0.1.dist-info/DESCRIPTION.rst
font_source_sans_pro-0.0.1.dist-info/METADATA
font_source_sans_pro-0.0.1.dist-info/RECORD
font_source_sans_pro-0.0.1.dist-info/WHEEL
font_source_sans_pro-0.0.1.dist-info/entry_points.txt
font_source_sans_pro-0.0.1.dist-info/metadata.json
font_source_sans_pro-0.0.1.dist-info/top_level.txt
